invisible_captcha_bypasser/__init__.py
invisible_captcha_bypasser/captcha_solver.py
invisible_captcha_bypasser-0.0.2.dist-info/METADATA
invisible_captcha_bypasser-0.0.2.dist-info/WHEEL
invisible_captcha_bypasser-0.0.2.dist-info/top_level.txt
invisible_captcha_bypasser-0.0.2.dist-info/RECORD
