Metadata-Version: 2.1
Name: invisible_captcha_bypasser
Version: 0.0.2
Summary: Bypassing invisible recaptcha v3
Home-page: https://github.com/nazavod777/invisible_captcha_bypasser
Author: nazavod
Author-email: n4z4v0d@gmail.com
Project-URL: GitHub, https://github.com/nazavod777/invisible_captcha_bypasser
Keywords: captcha recaptcha bypass recaptchav3 invisible_captcha
Classifier: Programming Language :: Python :: 3.11
Classifier: License :: OSI Approved :: MIT License
Classifier: Operating System :: OS Independent
Requires-Python: >=3.6
Requires-Dist: curl-cffi (>=0.5.9)
Requires-Dist: aiohttp-proxy (>=0.1.2)
Requires-Dist: better-proxy (>=1.1.0)
